{
  "Version": 3,
  "Meta": {
    "Duration": 4.467,
    "Fps": 30.0,
    "Loop": true,
    "AreBeziersRestricted": true,
    "CurveCount": 114,
    "TotalSegmentCount": 345,
    "TotalPointCount": 485,
    "UserDataCount": 1,
    "TotalUserDataSize": 0
  },
  "Curves": [
    {
      "Target": "Parameter",
      "Id": "Param122",
      "Segments": [
        0,
        0.813,
        0,
        0.9,
        7,
        2,
        2.633,
        7,
        0,
        4.467,
        0.813
      ]
    },
    {
      "Target": "Parameter",
      "Id": "Param123",
      "Segments": [
        0,
        -1.22,
        0,
        0.9,
        -5,
        0,
        4.467,
        -1.22
      ]
    },
    {
      "Target": "Parameter",
      "Id": "Param124",
      "Segments": [
        0,
        0,
        0,
        0.9,
        14,
        0,
        1.467,
        10,
        0,
        2.2,
        13,
        0,
        4.467,
        0
      ]
    },
    {
      "Target": "Parameter",
      "Id": "ParamAngleY",
      "Segments": [
        0,
        0.635,
        0,
        0.367,
        11.916,
        0,
        0.867,
        -1.42,
        0,
        1.133,
        0.635,
        2,
        1.633,
        0.635,
        2,
        3.133,
        0.635,
        2,
        4.467,
        0.635
      ]
    },
    {
      "Target": "Parameter",
      "Id": "ParamAngleZ",
      "Segments": [
        0,
        -0.938,
        0,
        0.367,
        -3,
        0,
        0.867,
        18.022,
        1,
        1.056,
        18.022,
        1.244,
        16.872,
        1.433,
        14.961,
        1,
        1.533,
        13.949,
        1.633,
        13.605,
        1.733,
        13.605,
        1,
        2.155,
        13.605,
        2.578,
        13.827,
        3,
        14.604,
        1,
        3.078,
        14.747,
        3.155,
        17.064,
        3.233,
        17.064,
        1,
        3.355,
        17.064,
        3.478,
        17.579,
        3.6,
        14.604,
        1,
        3.8,
        9.736,
        4,
        -3,
        4.2,
        -3,
        0,
        4.467,
        -0.938
      ]
    },
    {
      "Target": "Parameter",
      "Id": "Param27",
      "Segments": [
        0,
        -22.6,
        2,
        0.533,
        -22.6,
        1,
        0.644,
        -22.6,
        0.756,
        -2.823,
        0.867,
        0.499,
        1,
        1.056,
        6.147,
        1.244,
        12.026,
        1.433,
        12.834,
        1,
        2.111,
        15.731,
        2.789,
        16.4,
        3.467,
        16.4,
        2,
        4.467,
        16.4
      ]
    },
    {
      "Target": "Parameter",
      "Id": "ParamBrowRY",
      "Segments": [
        0,
        0,
        0,
        0.233,
        0.14,
        0,
        0.567,
        0,
        2,
        0.867,
        0,
        2,
        1.633,
        0,
        2,
        3.133,
        0,
        2,
        4.467,
        0
      ]
    },
    {
      "Target": "Parameter",
      "Id": "ParamBrowLY",
      "Segments": [
        0,
        0,
        0,
        0.233,
        0.2,
        0,
        0.567,
        0,
        2,
        0.867,
        0,
        2,
        1.633,
        0,
        2,
        3.133,
        0,
        2,
        4.467,
        0
      ]
    },
    {
      "Target": "Parameter",
      "Id": "ParamEyeLOpen",
      "Segments": [
        0,
        1,
        0,
        0.233,
        1.1,
        0,
        0.5,
        1,
        2,
        0.867,
        1,
        2,
        1.633,
        1,
        2,
        3.133,
        1,
        2,
        4.467,
        1
      ]
    },
    {
      "Target": "Parameter",
      "Id": "ParamEyeROpen",
      "Segments": [
        0,
        1,
        0,
        0.233,
        1.1,
        1,
        0.322,
        1.1,
        0.411,
        1.09,
        0.5,
        1,
        1,
        0.533,
        0.966,
        0.567,
        0,
        0.6,
        0,
        2,
        1.633,
        0,
        2,
        3.133,
        0,
        2,
        3.567,
        0,
        0,
        3.9,
        1,
        2,
        4.167,
        1,
        2,
        4.467,
        1
      ]
    },
    {
      "Target": "Parameter",
      "Id": "ParamEyeRSmile",
      "Segments": [
        0,
        0,
        0,
        0.467,
        1,
        2,
        0.867,
        1,
        2,
        1.633,
        1,
        2,
        3.133,
        1,
        0,
        4.467,
        0
      ]
    },
    {
      "Target": "Parameter",
      "Id": "ParamMouthOpenY",
      "Segments": [
        0,
        1,
        0,
        0.1,
        0,
        2,
        0.3,
        0,
        0,
        0.4,
        0.839,
        0,
        0.667,
        0.621,
        0,
        0.733,
        0.98,
        0,
        0.867,
        0.558,
        0,
        1,
        0.663,
        0,
        1.467,
        0,
        2,
        1.533,
        0,
        0,
        1.667,
        0.012,
        0,
        1.733,
        0.004,
        0,
        1.8,
        0.749,
        0,
        1.933,
        0.502,
        1,
        1.966,
        0.502,
        2,
        0.825,
        2.033,
        0.831,
        1,
        2.078,
        0.839,
        2.122,
        0.838,
        2.167,
        0.838,
        1,
        2.222,
        0.838,
        2.278,
        0.033,
        2.333,
        0.012,
        1,
        2.378,
        0,
        2.422,
        0,
        2.467,
        0,
        2,
        2.6,
        0,
        0,
        2.8,
        0.867,
        0,
        2.867,
        0.847,
        0,
        3,
        0.894,
        0,
        3.067,
        0.831,
        0,
        3.2,
        0.977,
        0,
        3.267,
        0.804,
        0,
        3.367,
        0.867,
        0,
        3.467,
        0.377,
        1,
        3.511,
        0.377,
        3.556,
        0.651,
        3.6,
        0.835,
        1,
        3.633,
        0.973,
        3.667,
        0.97,
        3.7,
        0.97,
        0,
        3.967,
        0,
        0,
        4.467,
        1
      ]
    },
    {
      "Target": "Parameter",
      "Id": "ParamMouthForm",
      "Segments": [
        0,
        0,
        0,
        0.567,
        0.886,
        2,
        3.3,
        0.886,
        0,
        4.467,
        0
      ]
    },
    {
      "Target": "Parameter",
      "Id": "Param76",
      "Segments": [
        0,
        0,
        0,
        0.3,
        -0.3,
        0,
        0.4,
        0.7,
        2,
        1.1,
        0.7,
        1,
        1.211,
        0.7,
        1.322,
        0.08,
        1.433,
        -0.3,
        1,
        1.5,
        -0.528,
        1.566,
        -0.546,
        1.633,
        -0.7,
        1,
        1.655,
        -0.751,
        1.678,
        -0.848,
        1.7,
        -0.848,
        1,
        1.767,
        -0.848,
        1.833,
        -0.861,
        1.9,
        -0.8,
        1,
        1.967,
        -0.739,
        2.033,
        0.795,
        2.1,
        0.795,
        0,
        2.4,
        0.641,
        0,
        2.6,
        0.795,
        1,
        2.678,
        0.795,
        2.755,
        0.763,
        2.833,
        0.466,
        1,
        2.866,
        0.339,
        2.9,
        -0.779,
        2.933,
        -0.779,
        1,
        2.978,
        -0.779,
        3.022,
        -0.022,
        3.067,
        0.234,
        1,
        3.111,
        0.489,
        3.156,
        0.472,
        3.2,
        0.472,
        0,
        3.5,
        -0.8,
        1,
        3.567,
        -0.8,
        3.633,
        0.269,
        3.7,
        0.492,
        1,
        3.756,
        0.679,
        3.811,
        0.641,
        3.867,
        0.641,
        0,
        4.133,
        -0.5,
        2,
        4.233,
        -0.5,
        0,
        4.467,
        0
      ]
    },
    {
      "Target": "Parameter",
      "Id": "ParamBodyAngleX",
      "Segments": [
        0,
        -2.025,
        0,
        0.367,
        3.518,
        0,
        0.9,
        -3.337,
        2,
        1.5,
        -3.337,
        2,
        3.133,
        -3.337,
        1,
        3.211,
        -3.337,
        3.289,
        -3.364,
        3.367,
        -2.396,
        1,
        3.522,
        -0.461,
        3.678,
        1.641,
        3.833,
        1.641,
        0,
        4.467,
        -2.025
      ]
    },
    {
      "Target": "Parameter",
      "Id": "ParamBodyAngleY",
      "Segments": [
        0,
        -0.602,
        1,
        0.1,
        -0.602,
        0.2,
        -0.471,
        0.3,
        0.681,
        1,
        0.4,
        1.832,
        0.5,
        4.651,
        0.6,
        6.062,
        1,
        0.689,
        7.316,
        0.778,
        7.587,
        0.867,
        7.587,
        0,
        1.633,
        6.378,
        2,
        1.9,
        6.378,
        0,
        3.067,
        6.939,
        1,
        3.211,
        6.939,
        3.356,
        7.027,
        3.5,
        5.152,
        1,
        3.667,
        2.989,
        3.833,
        -1.776,
        4,
        -1.776,
        0,
        4.467,
        -0.602
      ]
    },
    {
      "Target": "Parameter",
      "Id": "ParamBodyAngleZ",
      "Segments": [
        0,
        -0.061,
        0,
        0.867,
        -0.041,
        2,
        1.633,
        -0.041,
        2,
        3.6,
        -0.041,
        0,
        4.467,
        -0.061
      ]
    },
    {
      "Target": "Parameter",
      "Id": "ParamBodyAngleX2",
      "Segments": [
        0,
        -3.021,
        0,
        0.367,
        0.595,
        1,
        0.445,
        0.595,
        0.522,
        -4.43,
        0.6,
        -5.499,
        1,
        0.689,
        -6.72,
        0.778,
        -6.663,
        0.867,
        -6.663,
        2,
        3.133,
        -6.663,
        0,
        3.933,
        -1.14,
        0,
        4.467,
        -3.021
      ]
    },
    {
      "Target": "Parameter",
      "Id": "Param112",
      "Segments": [
        0,
        -0.106,
        0,
        0.267,
        -11,
        0,
        0.767,
        8.565,
        0,
        1.6,
        6,
        0,
        3.267,
        7.572,
        0,
        4.467,
        -0.106
      ]
    },
    {
      "Target": "Parameter",
      "Id": "Param113",
      "Segments": [
        0,
        -0.894,
        0,
        0.267,
        -9,
        0,
        0.767,
        3.335,
        0,
        1.5,
        2.595,
        0,
        3.233,
        4.37,
        1,
        3.311,
        4.37,
        3.389,
        4.159,
        3.467,
        1.311,
        1,
        3.578,
        -2.759,
        3.689,
        -7.514,
        3.8,
        -7.514,
        1,
        3.9,
        -7.514,
        4,
        -4.857,
        4.1,
        -1.677,
        1,
        4.156,
        0.09,
        4.211,
        0.349,
        4.267,
        0.349,
        0,
        4.467,
        -0.894
      ]
    },
    {
      "Target": "Parameter",
      "Id": "Param114",
      "Segments": [
        0,
        -3.446,
        0,
        0.1,
        3.5,
        1,
        0.156,
        3.5,
        0.211,
        -12.176,
        0.267,
        -16,
        1,
        0.311,
        -19.059,
        0.356,
        -18.688,
        0.4,
        -18.688,
        1,
        0.456,
        -18.688,
        0.511,
        -15.931,
        0.567,
        -9.964,
        1,
        0.634,
        -2.802,
        0.7,
        11.014,
        0.767,
        12,
        1,
        0.922,
        14.3,
        1.078,
        14.621,
        1.233,
        14.621,
        1,
        1.355,
        14.621,
        1.478,
        14.128,
        1.6,
        12,
        1,
        1.7,
        10.259,
        1.8,
        8.388,
        1.9,
        8.388,
        0,
        3.4,
        14.621,
        0,
        3.8,
        -11.446,
        0,
        4.2,
        1.748,
        0,
        4.467,
        -3.446
      ]
    },
    {
      "Target": "Parameter",
      "Id": "Param115",
      "Segments": [
        0,
        -3.702,
        0,
        0.267,
        -30,
        2,
        0.367,
        -30,
        0,
        0.6,
        30,
        0,
        0.767,
        0,
        2,
        1.3,
        0,
        0,
        1.667,
        -6.691,
        0,
        3.133,
        0,
        1,
        3.211,
        0,
        3.289,
        0.086,
        3.367,
        -0.3,
        1,
        3.734,
        -2.118,
        4.1,
        -3.702,
        4.467,
        -3.702
      ]
    },
    {
      "Target": "Parameter",
      "Id": "Param77",
      "Segments": [
        0,
        0,
        0,
        0.767,
        -9,
        2,
        1.5,
        -9,
        2,
        3.133,
        -9,
        1,
        3.211,
        -9,
        3.289,
        -9.205,
        3.367,
        -8.271,
        1,
        3.734,
        -3.871,
        4.1,
        0,
        4.467,
        0
      ]
    },
    {
      "Target": "Parameter",
      "Id": "Param26",
      "Segments": [
        0,
        0,
        0,
        0.767,
        30,
        2,
        1.5,
        30,
        2,
        3.133,
        30,
        1,
        3.211,
        30,
        3.289,
        30.628,
        3.367,
        27.57,
        1,
        3.734,
        13.156,
        4.1,
        0,
        4.467,
        0
      ]
    },
    {
      "Target": "Parameter",
      "Id": "Param128",
      "Segments": [
        0,
        1,
        2,
        0.467,
        1,
        0,
        0.5,
        0,
        2,
        0.767,
        0,
        2,
        1.5,
        0,
        2,
        3.133,
        0,
        1,
        3.311,
        0,
        3.489,
        0.024,
        3.667,
        0.081,
        1,
        3.678,
        0.085,
        3.689,
        1,
        3.7,
        1,
        2,
        4.467,
        1
      ]
    },
    {
      "Target": "Parameter",
      "Id": "Param129",
      "Segments": [
        0,
        0,
        2,
        0.467,
        0,
        0,
        0.5,
        1,
        2,
        0.767,
        1,
        2,
        1.5,
        1,
        2,
        3.133,
        1,
        1,
        3.311,
        1,
        3.489,
        0.976,
        3.667,
        0.919,
        1,
        3.678,
        0.915,
        3.689,
        0,
        3.7,
        0,
        2,
        4.467,
        0
      ]
    },
    {
      "Target": "Parameter",
      "Id": "Param116",
      "Segments": [
        0,
        -0.551,
        0,
        0.233,
        -4.55,
        0,
        0.7,
        0.941,
        0,
        1.367,
        -1.412,
        0,
        3.2,
        0.941,
        0,
        4.2,
        -1.412,
        0,
        4.467,
        -0.551
      ]
    },
    {
      "Target": "Parameter",
      "Id": "Param117",
      "Segments": [
        0,
        -1.252,
        0,
        0.333,
        -2.124,
        0,
        0.867,
        9.826,
        0,
        1.633,
        6,
        0,
        3.333,
        7.296,
        0,
        4.467,
        -1.252
      ]
    },
    {
      "Target": "Parameter",
      "Id": "Param118",
      "Segments": [
        0,
        -20.377,
        2,
        0.033,
        -20.377,
        0,
        0.433,
        -28.396,
        0,
        0.967,
        -17.389,
        0,
        1.733,
        -28.396,
        0,
        3.8,
        -14.693,
        0,
        4.467,
        -20.377
      ]
    },
    {
      "Target": "Parameter",
      "Id": "Param11",
      "Segments": [
        0,
        1.522,
        0,
        0.367,
        -6,
        0,
        0.867,
        3.022,
        1,
        1.089,
        3.022,
        1.311,
        1.869,
        1.533,
        -0.045,
        1,
        1.633,
        -0.907,
        1.733,
        -1.178,
        1.833,
        -1.178,
        0,
        2.6,
        -0.045,
        0,
        3,
        -1.178,
        1,
        3.144,
        -1.178,
        3.289,
        -1.267,
        3.433,
        -0.448,
        1,
        3.611,
        0.56,
        3.789,
        3.022,
        3.967,
        3.022,
        0,
        4.467,
        1.522
      ]
    },
    {
      "Target": "Parameter",
      "Id": "Param13",
      "Segments": [
        0,
        6.327,
        1,
        0.067,
        6.327,
        0.133,
        6.562,
        0.2,
        4.817,
        1,
        0.278,
        2.782,
        0.355,
        -9.492,
        0.433,
        -9.492,
        0,
        1.033,
        7.945,
        1,
        1.233,
        7.945,
        1.433,
        2.597,
        1.633,
        -1.885,
        1,
        1.744,
        -4.375,
        1.856,
        -4.336,
        1.967,
        -4.336,
        0,
        2.667,
        -2.727,
        0,
        3.267,
        -7.711,
        0,
        4.333,
        7.359,
        0,
        4.467,
        6.327
      ]
    },
    {
      "Target": "Parameter",
      "Id": "Param15",
      "Segments": [
        0,
        10.182,
        1,
        0.078,
        10.182,
        0.155,
        10.342,
        0.233,
        6.667,
        1,
        0.322,
        2.467,
        0.411,
        -9.307,
        0.5,
        -9.307,
        0,
        1.233,
        14.528,
        0,
        2.167,
        -1.428,
        0,
        2.867,
        0.649,
        0,
        3.533,
        -1.428,
        0,
        4.467,
        10.182
      ]
    },
    {
      "Target": "Parameter",
      "Id": "Param12",
      "Segments": [
        0,
        2.025,
        0,
        0.367,
        -6,
        0,
        0.933,
        5.625,
        1,
        1.078,
        5.625,
        1.222,
        5.055,
        1.367,
        3.533,
        1,
        1.545,
        1.659,
        1.722,
        0.495,
        1.9,
        0.495,
        0,
        2.667,
        1.268,
        2,
        3.2,
        1.268,
        0,
        3.833,
        4.197,
        0,
        4.467,
        2.025
      ]
    },
    {
      "Target": "Parameter",
      "Id": "Param14",
      "Segments": [
        0,
        2.067,
        0,
        0.467,
        -3.898,
        0,
        1.233,
        6.2,
        0,
        2.2,
        -0.066,
        0,
        2.733,
        0.824,
        0,
        3.4,
        -2.407,
        0,
        4.233,
        4.209,
        0,
        4.467,
        2.067
      ]
    },
    {
      "Target": "Parameter",
      "Id": "Param16",
      "Segments": [
        0,
        -2.214,
        0,
        0.2,
        2.65,
        0,
        0.567,
        -15.592,
        0,
        1.433,
        9.396,
        0,
        2.467,
        -2.972,
        0,
        2.9,
        -1.958,
        0,
        3.667,
        -8.847,
        0,
        4.467,
        -2.214
      ]
    },
    {
      "Target": "Parameter",
      "Id": "ParamAngleX",
      "Segments": [
        0,
        -9.347,
        0,
        4.467,
        -9.347
      ]
    },
    {
      "Target": "Parameter",
      "Id": "ParamCheek",
      "Segments": [
        0,
        0,
        0,
        4.467,
        0
      ]
    },
    {
      "Target": "Parameter",
      "Id": "Param53",
      "Segments": [
        0,
        -30,
        0,
        4.467,
        -30
      ]
    },
    {
      "Target": "Parameter",
      "Id": "Param55",
      "Segments": [
        0,
        -30,
        0,
        4.467,
        -30
      ]
    },
    {
      "Target": "Parameter",
      "Id": "Param56",
      "Segments": [
        0,
        -30,
        0,
        4.467,
        -30
      ]
    },
    {
      "Target": "Parameter",
      "Id": "Param57",
      "Segments": [
        0,
        -30,
        0,
        4.467,
        -30
      ]
    },
    {
      "Target": "Parameter",
      "Id": "Param61",
      "Segments": [
        0,
        0,
        0,
        4.467,
        0
      ]
    },
    {
      "Target": "Parameter",
      "Id": "Param58",
      "Segments": [
        0,
        0,
        0,
        4.467,
        0
      ]
    },
    {
      "Target": "Parameter",
      "Id": "Param59",
      "Segments": [
        0,
        0,
        0,
        4.467,
        0
      ]
    },
    {
      "Target": "Parameter",
      "Id": "Param60",
      "Segments": [
        0,
        0,
        0,
        4.467,
        0
      ]
    },
    {
      "Target": "Parameter",
      "Id": "Param65",
      "Segments": [
        0,
        0,
        0,
        4.467,
        0
      ]
    },
    {
      "Target": "Parameter",
      "Id": "Param62",
      "Segments": [
        0,
        0,
        0,
        4.467,
        0
      ]
    },
    {
      "Target": "Parameter",
      "Id": "Param66",
      "Segments": [
        0,
        0,
        0,
        4.467,
        0
      ]
    },
    {
      "Target": "Parameter",
      "Id": "Param64",
      "Segments": [
        0,
        0,
        0,
        4.467,
        0
      ]
    },
    {
      "Target": "Parameter",
      "Id": "Param69",
      "Segments": [
        0,
        0,
        0,
        4.467,
        0
      ]
    },
    {
      "Target": "Parameter",
      "Id": "Param63",
      "Segments": [
        0,
        0,
        0,
        4.467,
        0
      ]
    },
    {
      "Target": "Parameter",
      "Id": "Param67",
      "Segments": [
        0,
        0,
        0,
        4.467,
        0
      ]
    },
    {
      "Target": "Parameter",
      "Id": "Param68",
      "Segments": [
        0,
        0,
        0,
        4.467,
        0
      ]
    },
    {
      "Target": "Parameter",
      "Id": "Param70",
      "Segments": [
        0,
        0,
        0,
        4.467,
        0
      ]
    },
    {
      "Target": "Parameter",
      "Id": "Param71",
      "Segments": [
        0,
        0,
        0,
        4.467,
        0
      ]
    },
    {
      "Target": "Parameter",
      "Id": "Param72",
      "Segments": [
        0,
        0,
        0,
        4.467,
        0
      ]
    },
    {
      "Target": "Parameter",
      "Id": "Param82",
      "Segments": [
        0,
        0,
        0,
        4.467,
        0
      ]
    },
    {
      "Target": "Parameter",
      "Id": "Param73",
      "Segments": [
        0,
        0,
        0,
        4.467,
        0
      ]
    },
    {
      "Target": "Parameter",
      "Id": "Param84",
      "Segments": [
        0,
        0,
        0,
        4.467,
        0
      ]
    },
    {
      "Target": "Parameter",
      "Id": "Param74",
      "Segments": [
        0,
        0,
        0,
        4.467,
        0
      ]
    },
    {
      "Target": "Parameter",
      "Id": "Param85",
      "Segments": [
        0,
        0,
        0,
        4.467,
        0
      ]
    },
    {
      "Target": "Parameter",
      "Id": "Param75",
      "Segments": [
        0,
        0,
        0,
        4.467,
        0
      ]
    },
    {
      "Target": "Parameter",
      "Id": "Param86",
      "Segments": [
        0,
        0,
        0,
        4.467,
        0
      ]
    },
    {
      "Target": "Parameter",
      "Id": "ParamBrowRX",
      "Segments": [
        0,
        0,
        0,
        4.467,
        0
      ]
    },
    {
      "Target": "Parameter",
      "Id": "ParamBrowRAngle",
      "Segments": [
        0,
        0,
        0,
        4.467,
        0
      ]
    },
    {
      "Target": "Parameter",
      "Id": "ParamBrowRForm",
      "Segments": [
        0,
        0,
        0,
        4.467,
        0
      ]
    },
    {
      "Target": "Parameter",
      "Id": "ParamBrowLX",
      "Segments": [
        0,
        0,
        0,
        4.467,
        0
      ]
    },
    {
      "Target": "Parameter",
      "Id": "ParamBrowLAngle",
      "Segments": [
        0,
        0,
        0,
        4.467,
        0
      ]
    },
    {
      "Target": "Parameter",
      "Id": "ParamBrowLForm",
      "Segments": [
        0,
        0,
        0,
        4.467,
        0
      ]
    },
    {
      "Target": "Parameter",
      "Id": "Param147",
      "Segments": [
        0,
        0,
        0,
        4.467,
        0
      ]
    },
    {
      "Target": "Parameter",
      "Id": "ParamEyeLSmile",
      "Segments": [
        0,
        0,
        0,
        4.467,
        0
      ]
    },
    {
      "Target": "Parameter",
      "Id": "ParamEyeBallX",
      "Segments": [
        0,
        0.059,
        0,
        4.467,
        0.059
      ]
    },
    {
      "Target": "Parameter",
      "Id": "ParamEyeBallY",
      "Segments": [
        0,
        0,
        0,
        4.467,
        0
      ]
    },
    {
      "Target": "Parameter",
      "Id": "Param120",
      "Segments": [
        0,
        0,
        0,
        4.467,
        0
      ]
    },
    {
      "Target": "Parameter",
      "Id": "Param",
      "Segments": [
        0,
        0,
        0,
        4.467,
        0
      ]
    },
    {
      "Target": "Parameter",
      "Id": "Param146",
      "Segments": [
        0,
        0,
        0,
        4.467,
        0
      ]
    },
    {
      "Target": "Parameter",
      "Id": "Param148",
      "Segments": [
        0,
        0,
        0,
        4.467,
        0
      ]
    },
    {
      "Target": "Parameter",
      "Id": "Param139",
      "Segments": [
        0,
        0,
        0,
        4.467,
        0
      ]
    },
    {
      "Target": "Parameter",
      "Id": "Param80",
      "Segments": [
        0,
        0,
        0,
        4.467,
        0
      ]
    },
    {
      "Target": "Parameter",
      "Id": "Param145",
      "Segments": [
        0,
        -30,
        0,
        4.467,
        -30
      ]
    },
    {
      "Target": "Parameter",
      "Id": "Param140",
      "Segments": [
        0,
        0,
        0,
        4.467,
        0
      ]
    },
    {
      "Target": "Parameter",
      "Id": "Param142",
      "Segments": [
        0,
        0,
        0,
        4.467,
        0
      ]
    },
    {
      "Target": "Parameter",
      "Id": "Param141",
      "Segments": [
        0,
        0,
        0,
        4.467,
        0
      ]
    },
    {
      "Target": "Parameter",
      "Id": "Param143",
      "Segments": [
        0,
        0,
        0,
        4.467,
        0
      ]
    },
    {
      "Target": "Parameter",
      "Id": "Param144",
      "Segments": [
        0,
        0,
        0,
        4.467,
        0
      ]
    },
    {
      "Target": "Parameter",
      "Id": "Param2",
      "Segments": [
        0,
        0,
        0,
        4.467,
        0
      ]
    },
    {
      "Target": "Parameter",
      "Id": "Param46",
      "Segments": [
        0,
        -9,
        0,
        4.467,
        -9
      ]
    },
    {
      "Target": "Parameter",
      "Id": "Param81",
      "Segments": [
        0,
        -9,
        0,
        4.467,
        -9
      ]
    },
    {
      "Target": "Parameter",
      "Id": "Param50",
      "Segments": [
        0,
        0,
        0,
        4.467,
        0
      ]
    },
    {
      "Target": "Parameter",
      "Id": "Param89",
      "Segments": [
        0,
        0,
        0,
        4.467,
        0
      ]
    },
    {
      "Target": "Parameter",
      "Id": "Param111",
      "Segments": [
        0,
        0,
        0,
        4.467,
        0
      ]
    },
    {
      "Target": "Parameter",
      "Id": "ParamBodyAngleY2",
      "Segments": [
        0,
        1.014,
        0,
        4.467,
        1.014
      ]
    },
    {
      "Target": "Parameter",
      "Id": "ParamBreath",
      "Segments": [
        0,
        0,
        0,
        4.467,
        0
      ]
    },
    {
      "Target": "Parameter",
      "Id": "Param119",
      "Segments": [
        0,
        -2.67,
        0,
        4.467,
        -2.67
      ]
    },
    {
      "Target": "Parameter",
      "Id": "Param87",
      "Segments": [
        0,
        0,
        0,
        4.467,
        0
      ]
    },
    {
      "Target": "Parameter",
      "Id": "Param78",
      "Segments": [
        0,
        0,
        0,
        4.467,
        0
      ]
    },
    {
      "Target": "Parameter",
      "Id": "Param17",
      "Segments": [
        0,
        1,
        0,
        4.467,
        1
      ]
    },
    {
      "Target": "Parameter",
      "Id": "Param79",
      "Segments": [
        0,
        1,
        0,
        4.467,
        1
      ]
    },
    {
      "Target": "Parameter",
      "Id": "Param54",
      "Segments": [
        0,
        0,
        0,
        4.467,
        0
      ]
    },
    {
      "Target": "Parameter",
      "Id": "Param149",
      "Segments": [
        0,
        0,
        0,
        4.467,
        0
      ]
    },
    {
      "Target": "Parameter",
      "Id": "Param8",
      "Segments": [
        0,
        0,
        0,
        4.467,
        0
      ]
    },
    {
      "Target": "Parameter",
      "Id": "Param83",
      "Segments": [
        0,
        0,
        0,
        4.467,
        0
      ]
    },
    {
      "Target": "Parameter",
      "Id": "Param6",
      "Segments": [
        0,
        0,
        0,
        4.467,
        0
      ]
    },
    {
      "Target": "Parameter",
      "Id": "Param7",
      "Segments": [
        0,
        0,
        0,
        4.467,
        0
      ]
    },
    {
      "Target": "Parameter",
      "Id": "Param130",
      "Segments": [
        0,
        1,
        0,
        4.467,
        1
      ]
    },
    {
      "Target": "Parameter",
      "Id": "Param131",
      "Segments": [
        0,
        0,
        0,
        4.467,
        0
      ]
    },
    {
      "Target": "Parameter",
      "Id": "Param107",
      "Segments": [
        0,
        -2.847,
        0,
        4.467,
        -2.847
      ]
    },
    {
      "Target": "Parameter",
      "Id": "Param108",
      "Segments": [
        0,
        -17.122,
        0,
        4.467,
        -17.122
      ]
    },
    {
      "Target": "Parameter",
      "Id": "Param133",
      "Segments": [
        0,
        8.518,
        0,
        4.467,
        8.518
      ]
    },
    {
      "Target": "Parameter",
      "Id": "Param51",
      "Segments": [
        0,
        -6.596,
        0,
        4.467,
        -6.596
      ]
    },
    {
      "Target": "Parameter",
      "Id": "Param52",
      "Segments": [
        0,
        0,
        0,
        4.467,
        0
      ]
    },
    {
      "Target": "Parameter",
      "Id": "Param125",
      "Segments": [
        0,
        0,
        0,
        4.467,
        0
      ]
    },
    {
      "Target": "Parameter",
      "Id": "Param135",
      "Segments": [
        0,
        0,
        0,
        4.467,
        0
      ]
    },
    {
      "Target": "Parameter",
      "Id": "Param134",
      "Segments": [
        0,
        0,
        0,
        4.467,
        0
      ]
    }
  ],
  "UserData": [
    {
      "Time": 0.0,
      "Value": ""
    }
  ]
}