{
  "Version": 3,
  "Meta": {
    "Duration": 4.0,
    "Fps": 30.0,
    "Loop": true,
    "AreBeziersRestricted": true,
    "CurveCount": 124,
    "TotalSegmentCount": 479,
    "TotalPointCount": 729,
    "UserDataCount": 1,
    "TotalUserDataSize": 0
  },
  "Curves": [
    {
      "Target": "Parameter",
      "Id": "ParamAngleX",
      "Segments": [
        0,
        2.868,
        1,
        0.089,
        2.868,
        0.178,
        -13.413,
        0.267,
        -15.705,
        1,
        0.6,
        -24.354,
        0.934,
        -30,
        1.267,
        -30,
        0,
        2.7,
        6.04,
        0,
        4,
        2.868
      ]
    },
    {
      "Target": "Parameter",
      "Id": "ParamAngleY",
      "Segments": [
        0,
        12.341,
        0,
        0.633,
        -30,
        0,
        1.367,
        26.899,
        0,
        1.967,
        20.134,
        0,
        2.667,
        30,
        0,
        3.367,
        -8.215,
        0,
        4,
        12.341
      ]
    },
    {
      "Target": "Parameter",
      "Id": "ParamAngleZ",
      "Segments": [
        0,
        0,
        0,
        1.267,
        30,
        2,
        3.3,
        30,
        0,
        4,
        0
      ]
    },
    {
      "Target": "Parameter",
      "Id": "ParamEyeLOpen",
      "Segments": [
        0,
        1,
        0,
        0.3,
        0,
        2,
        1.267,
        0,
        0,
        2.067,
        1,
        2,
        3.033,
        1,
        0,
        3.333,
        0.8,
        0,
        4,
        1
      ]
    },
    {
      "Target": "Parameter",
      "Id": "ParamEyeROpen",
      "Segments": [
        0,
        1,
        0,
        0.3,
        0,
        2,
        1.267,
        0,
        0,
        2.067,
        1,
        2,
        3.033,
        1,
        0,
        3.333,
        0.8,
        0,
        4,
        1
      ]
    },
    {
      "Target": "Parameter",
      "Id": "ParamEyeBallX",
      "Segments": [
        0,
        0.638,
        0,
        0.3,
        -0.3,
        2,
        1.267,
        -0.3,
        1,
        1.534,
        -0.3,
        1.8,
        0.686,
        2.067,
        0.8,
        1,
        2.711,
        1,
        3.356,
        0.638,
        4,
        0.638
      ]
    },
    {
      "Target": "Parameter",
      "Id": "ParamEyeBallY",
      "Segments": [
        0,
        -0.161,
        0,
        0.3,
        -0.4,
        2,
        1.267,
        -0.4,
        0,
        2.067,
        -0.1,
        0,
        4,
        -0.161
      ]
    },
    {
      "Target": "Parameter",
      "Id": "ParamCheek",
      "Segments": [
        0,
        0.5,
        2,
        0.6,
        0.5,
        0,
        3.3,
        0.8,
        0,
        4,
        0.5
      ]
    },
    {
      "Target": "Parameter",
      "Id": "ParamMouthOpenY",
      "Segments": [
        0,
        0,
        2,
        0.033,
        0,
        2,
        0.433,
        0,
        0,
        0.5,
        0.672,
        0,
        0.567,
        0.158,
        0,
        0.767,
        0.94,
        0,
        0.833,
        0.004,
        0,
        0.9,
        1,
        0,
        1.1,
        0,
        0,
        1.233,
        0.729,
        0,
        1.433,
        0.017,
        0,
        1.567,
        0.743,
        0,
        1.633,
        0.667,
        0,
        1.7,
        0.851,
        0,
        1.833,
        0,
        2,
        2.233,
        0,
        2,
        4,
        0
      ]
    },
    {
      "Target": "Parameter",
      "Id": "ParamMouthForm",
      "Segments": [
        0,
        0,
        0,
        0.433,
        -0.255,
        0,
        0.7,
        0.311,
        1,
        0.711,
        0.311,
        0.722,
        0.202,
        0.733,
        0.164,
        1,
        0.778,
        0.011,
        0.822,
        -0.233,
        0.867,
        -0.236,
        1,
        0.967,
        -0.244,
        1.067,
        -0.244,
        1.167,
        -0.244,
        0,
        1.2,
        0.228,
        0,
        1.633,
        -0.521,
        0,
        2.067,
        1,
        2,
        2.6,
        1,
        2,
        3.467,
        1,
        0,
        4,
        0
      ]
    },
    {
      "Target": "Parameter",
      "Id": "ParamBodyAngleX",
      "Segments": [
        0,
        0.956,
        1,
        0.356,
        0.956,
        0.711,
        -10,
        1.067,
        -8.913,
        1,
        1.445,
        -7.919,
        1.822,
        10,
        2.2,
        10,
        1,
        2.467,
        10,
        2.733,
        9.469,
        3,
        8.832,
        1,
        3.333,
        7.785,
        3.667,
        0.956,
        4,
        0.956
      ]
    },
    {
      "Target": "Parameter",
      "Id": "ParamBodyAngleY",
      "Segments": [
        0,
        10,
        0,
        0.833,
        4.913,
        0,
        2.167,
        10,
        0,
        3.133,
        7.839,
        0,
        4,
        10
      ]
    },
    {
      "Target": "Parameter",
      "Id": "ParamBodyAngleZ",
      "Segments": [
        0,
        2.482,
        1,
        0.2,
        2.482,
        0.4,
        -4.279,
        0.6,
        -2.604,
        1,
        0.967,
        0.469,
        1.333,
        8.175,
        1.7,
        9.718,
        2,
        2.6,
        9.718,
        0,
        4,
        2.482
      ]
    },
    {
      "Target": "Parameter",
      "Id": "ParamHipX",
      "Segments": [
        0,
        5.233,
        1,
        0.178,
        5.233,
        0.355,
        -1.232,
        0.533,
        -0.054,
        1,
        0.822,
        1.869,
        1.111,
        10,
        1.4,
        10,
        1,
        1.667,
        10,
        1.933,
        8.349,
        2.2,
        8.295,
        1,
        2.489,
        8.236,
        2.778,
        9.296,
        3.067,
        8.564,
        1,
        3.378,
        7.778,
        3.689,
        5.233,
        4,
        5.233
      ]
    },
    {
      "Target": "Parameter",
      "Id": "ParamHipY",
      "Segments": [
        0,
        2.246,
        0,
        0.667,
        -6.336,
        1,
        0.9,
        -4.398,
        1.134,
        9.987,
        1.367,
        9.987,
        1,
        1.534,
        9.987,
        1.7,
        8.559,
        1.867,
        8.537,
        1,
        2.078,
        8.509,
        2.289,
        9.935,
        2.5,
        9.852,
        0,
        4,
        2.246
      ]
    },
    {
      "Target": "Parameter",
      "Id": "ParamDX",
      "Segments": [
        0,
        0,
        1,
        0.311,
        0,
        0.622,
        0.645,
        0.933,
        0.872,
        1,
        1.666,
        1.41,
        2.4,
        0.872,
        3.133,
        0.872,
        0,
        4,
        0
      ]
    },
    {
      "Target": "Parameter",
      "Id": "ParamPJ1",
      "Segments": [
        0,
        0,
        0,
        0.467,
        -3,
        1,
        0.734,
        -3,
        1,
        1.156,
        1.267,
        5,
        1,
        1.556,
        9.164,
        1.844,
        10,
        2.133,
        10,
        1,
        2.422,
        10,
        2.711,
        8.079,
        3,
        5,
        1,
        3.333,
        1.447,
        3.667,
        0,
        4,
        0
      ]
    },
    {
      "Target": "Parameter",
      "Id": "ParamPJ5",
      "Segments": [
        0,
        0,
        1,
        0.422,
        0,
        0.845,
        3.249,
        1.267,
        7,
        1,
        1.556,
        9.567,
        1.844,
        10,
        2.133,
        10,
        1,
        2.422,
        10,
        2.711,
        9.733,
        3,
        7,
        1,
        3.333,
        3.847,
        3.667,
        0,
        4,
        0
      ]
    },
    {
      "Target": "Parameter",
      "Id": "ParamPJ2",
      "Segments": [
        0,
        0,
        2,
        0.467,
        0,
        0,
        1.267,
        10,
        0,
        2.433,
        -1,
        2,
        3,
        -1,
        0,
        4,
        0
      ]
    },
    {
      "Target": "Parameter",
      "Id": "ParamPJ6",
      "Segments": [
        0,
        0,
        0,
        0.467,
        -5,
        2,
        1.267,
        -5,
        2,
        3,
        -5,
        0,
        4,
        0
      ]
    },
    {
      "Target": "Parameter",
      "Id": "ParamPJ3",
      "Segments": [
        0,
        0,
        0,
        0.467,
        2,
        2,
        1.267,
        2,
        2,
        3,
        2,
        0,
        4,
        0
      ]
    },
    {
      "Target": "Parameter",
      "Id": "ParamPJ7",
      "Segments": [
        0,
        0,
        0,
        0.467,
        10,
        2,
        1.267,
        10,
        2,
        3,
        10,
        0,
        4,
        0
      ]
    },
    {
      "Target": "Parameter",
      "Id": "ParamPJ4",
      "Segments": [
        0,
        0,
        0,
        1.267,
        4.74,
        0,
        2.433,
        3,
        2,
        3,
        3,
        0,
        4,
        0
      ]
    },
    {
      "Target": "Parameter",
      "Id": "ParamPJ8",
      "Segments": [
        0,
        0,
        1,
        0.422,
        0,
        0.845,
        1.122,
        1.267,
        2.46,
        1,
        1.656,
        3.692,
        2.044,
        4,
        2.433,
        4,
        2,
        3,
        4,
        0,
        4,
        0
      ]
    },
    {
      "Target": "Parameter",
      "Id": "ParamArmL",
      "Segments": [
        0,
        -1.181,
        1,
        0.289,
        -1.742,
        0.578,
        -14.658,
        0.867,
        -20,
        1,
        1.056,
        -23.209,
        1.244,
        -24.159,
        1.433,
        -25.27,
        1,
        1.511,
        -25.728,
        1.589,
        -25.86,
        1.667,
        -26,
        1,
        2.111,
        -25.494,
        2.556,
        -27.12,
        3,
        -27.12,
        1,
        3.333,
        -27.12,
        3.667,
        -5.231,
        4,
        -1.181
      ]
    },
    {
      "Target": "Parameter",
      "Id": "ParamArmL1",
      "Segments": [
        0,
        1.552,
        1,
        0.289,
        -11.275,
        0.578,
        -19,
        0.867,
        -19,
        1,
        1.134,
        -19,
        1.4,
        -12.652,
        1.667,
        -12,
        1,
        2.111,
        -10.913,
        2.556,
        -11.028,
        3,
        -9.84,
        0,
        4,
        1.552
      ]
    },
    {
      "Target": "Parameter",
      "Id": "ParamHandL",
      "Segments": [
        0,
        -0.573,
        0,
        0.367,
        -20,
        0,
        0.867,
        -9,
        1,
        1.134,
        -9,
        1.4,
        -15.833,
        1.667,
        -18,
        1,
        2.111,
        -21.612,
        2.556,
        -21.96,
        3,
        -21.96,
        0,
        4,
        -0.573
      ]
    },
    {
      "Target": "Parameter",
      "Id": "ParamFingerL",
      "Segments": [
        0,
        -0.002,
        0,
        0.833,
        0,
        0,
        1.433,
        1,
        2,
        2.833,
        1,
        0,
        4,
        -0.002
      ]
    },
    {
      "Target": "Parameter",
      "Id": "ParamFingerL2",
      "Segments": [
        0,
        -0.002,
        0,
        0.833,
        0,
        1,
        1.033,
        0.123,
        1.233,
        0.588,
        1.433,
        0.588,
        2,
        2.833,
        0.588,
        0,
        4,
        -0.002
      ]
    },
    {
      "Target": "Parameter",
      "Id": "ParamFingerL3",
      "Segments": [
        0,
        0,
        2,
        0.833,
        0,
        1,
        1.033,
        0.148,
        1.233,
        0.706,
        1.433,
        0.706,
        2,
        2.833,
        0.706,
        0,
        4,
        0
      ]
    },
    {
      "Target": "Parameter",
      "Id": "ParamFingerL4",
      "Segments": [
        0,
        0,
        2,
        0.833,
        0,
        1,
        1.033,
        0.146,
        1.233,
        0.7,
        1.433,
        0.7,
        2,
        2.833,
        0.7,
        0,
        4,
        0
      ]
    },
    {
      "Target": "Parameter",
      "Id": "ParamFingerL5",
      "Segments": [
        0,
        0,
        2,
        0.833,
        0,
        1,
        1.033,
        0.188,
        1.233,
        0.9,
        1.433,
        0.9,
        2,
        2.833,
        0.9,
        0,
        4,
        0
      ]
    },
    {
      "Target": "Parameter",
      "Id": "Param",
      "Segments": [
        0,
        0,
        0,
        0.533,
        -10,
        2,
        3.433,
        -10,
        0,
        4,
        0
      ]
    },
    {
      "Target": "Parameter",
      "Id": "Param2",
      "Segments": [
        0,
        -0.758,
        0,
        1.233,
        -10,
        2,
        3.167,
        -10,
        1,
        3.445,
        -8.825,
        3.722,
        -0.758,
        4,
        -0.758
      ]
    },
    {
      "Target": "Parameter",
      "Id": "ParamZPJZ",
      "Segments": [
        0,
        0.165,
        0,
        1.667,
        -1,
        2,
        3,
        -1,
        0,
        4,
        0.165
      ]
    },
    {
      "Target": "Parameter",
      "Id": "ParamZPJZ2",
      "Segments": [
        0,
        0.206,
        1,
        0.056,
        0.206,
        0.111,
        0.814,
        0.167,
        0.94,
        1,
        0.234,
        1.09,
        0.3,
        0.841,
        0.367,
        2,
        1,
        0.522,
        4.698,
        0.678,
        10,
        0.833,
        10,
        2,
        3,
        10,
        1,
        3.178,
        10,
        3.355,
        8.6,
        3.533,
        6,
        1,
        3.689,
        3.724,
        3.844,
        0.206,
        4,
        0.206
      ]
    },
    {
      "Target": "Parameter",
      "Id": "ParamZPJW3",
      "Segments": [
        0,
        0,
        0,
        0.833,
        10,
        2,
        1.667,
        10,
        2,
        3.167,
        10,
        0,
        4,
        0
      ]
    },
    {
      "Target": "Parameter",
      "Id": "ZPJQX",
      "Segments": [
        0,
        0.948,
        1,
        0.122,
        0.948,
        0.245,
        -0.416,
        0.367,
        -0.6,
        1,
        0.522,
        -0.834,
        0.678,
        0.1,
        0.833,
        0.1,
        1,
        1.111,
        0.1,
        1.389,
        -0.476,
        1.667,
        -0.4,
        1,
        2.111,
        -0.186,
        2.556,
        -0.4,
        3,
        -0.4,
        0,
        4,
        0.948
      ]
    },
    {
      "Target": "Parameter",
      "Id": "ParamZPJW",
      "Segments": [
        0,
        -0.022,
        0,
        0.4,
        -6,
        1,
        0.789,
        -6,
        1.178,
        5.152,
        1.567,
        6,
        1,
        2.045,
        7.045,
        2.522,
        4.762,
        3,
        2.721,
        1,
        3.133,
        2.15,
        3.267,
        10,
        3.4,
        10,
        1,
        3.6,
        9.163,
        3.8,
        -0.022,
        4,
        -0.022
      ]
    },
    {
      "Target": "Parameter",
      "Id": "ParamZPJW4",
      "Segments": [
        0,
        -0.022,
        0,
        0.4,
        -10,
        0,
        1.567,
        10,
        0,
        3,
        3.664,
        0,
        3.233,
        10,
        0,
        4,
        -0.022
      ]
    },
    {
      "Target": "Parameter",
      "Id": "ParamSDS2",
      "Segments": [
        0,
        -0.641,
        0,
        0.233,
        -10,
        0,
        2.467,
        0,
        0,
        3.733,
        -10,
        0,
        4,
        -0.641
      ]
    },
    {
      "Target": "Parameter",
      "Id": "ParamSDS3",
      "Segments": [
        0,
        0,
        0,
        0.333,
        1,
        2,
        3.833,
        1,
        0,
        4,
        0
      ]
    },
    {
      "Target": "Parameter",
      "Id": "ParamZSDX",
      "Segments": [
        0,
        0,
        0,
        1.333,
        0.3,
        2,
        3,
        0.3,
        0,
        4,
        0
      ]
    },
    {
      "Target": "Parameter",
      "Id": "ParamArmR",
      "Segments": [
        0,
        -0.772,
        0,
        0.667,
        11.866,
        0,
        2.867,
        -7.087,
        0,
        4,
        -0.772
      ]
    },
    {
      "Target": "Parameter",
      "Id": "ParamArmRY",
      "Segments": [
        0,
        -0.082,
        0,
        0.7,
        -9,
        0,
        2.967,
        0,
        0,
        4,
        -0.082
      ]
    },
    {
      "Target": "Parameter",
      "Id": "ParamHandR",
      "Segments": [
        0,
        -0.573,
        0,
        1.1,
        -10,
        0,
        2.5,
        3,
        0,
        4,
        -0.573
      ]
    },
    {
      "Target": "Parameter",
      "Id": "ParamFingerR",
      "Segments": [
        0,
        0.18,
        2,
        1.433,
        0.18,
        0,
        2.167,
        0.6,
        0,
        4,
        0.18
      ]
    },
    {
      "Target": "Parameter",
      "Id": "ParamFingerR2",
      "Segments": [
        0,
        0.078,
        2,
        1.433,
        0.078,
        0,
        2.167,
        0.5,
        0,
        4,
        0.078
      ]
    },
    {
      "Target": "Parameter",
      "Id": "ParamFingerR3",
      "Segments": [
        0,
        0.062,
        2,
        1.567,
        0.062,
        0,
        2.3,
        0.5,
        0,
        4,
        0.062
      ]
    },
    {
      "Target": "Parameter",
      "Id": "ParamFingerR4",
      "Segments": [
        0,
        0.052,
        2,
        1.667,
        0.052,
        0,
        2.4,
        0.5,
        0,
        4,
        0.052
      ]
    },
    {
      "Target": "Parameter",
      "Id": "ParamFingerR5",
      "Segments": [
        0,
        0.052,
        2,
        1.8,
        0.052,
        0,
        2.533,
        0.5,
        0,
        4,
        0.052
      ]
    },
    {
      "Target": "Parameter",
      "Id": "ParamYPJ1",
      "Segments": [
        0,
        0.823,
        0,
        0.5,
        -30,
        1,
        1.033,
        -30,
        1.567,
        23.003,
        2.1,
        30,
        0,
        4,
        0.823
      ]
    },
    {
      "Target": "Parameter",
      "Id": "ParamYPJ2",
      "Segments": [
        0,
        0.823,
        0,
        0.5,
        -19,
        0,
        1.333,
        -30,
        1,
        1.589,
        -24.981,
        1.844,
        1.847,
        2.1,
        4,
        1,
        2.422,
        6.711,
        2.745,
        12.514,
        3.067,
        11,
        1,
        3.378,
        9.55,
        3.689,
        0.823,
        4,
        0.823
      ]
    },
    {
      "Target": "Parameter",
      "Id": "ParamPB11",
      "Segments": [
        0,
        0,
        0,
        1.533,
        2,
        0,
        4,
        0
      ]
    },
    {
      "Target": "Parameter",
      "Id": "ParamPB12",
      "Segments": [
        0,
        0,
        0,
        2,
        -0.45,
        0,
        4,
        0
      ]
    },
    {
      "Target": "Parameter",
      "Id": "ParamPB13",
      "Segments": [
        0,
        0,
        0,
        1.967,
        -1,
        0,
        4,
        0
      ]
    },
    {
      "Target": "Parameter",
      "Id": "ParamHY2",
      "Segments": [
        0,
        0,
        0,
        0.433,
        -0.389,
        1,
        0.666,
        -0.385,
        0.9,
        0.416,
        1.133,
        0.381,
        0,
        2.333,
        -0.127,
        0,
        4,
        0
      ]
    },
    {
      "Target": "Parameter",
      "Id": "ParamHY",
      "Segments": [
        0,
        -0.003,
        0,
        0.733,
        -0.306,
        0,
        1.3,
        0.434,
        0,
        2.5,
        -0.254,
        0,
        4,
        -0.003
      ]
    },
    {
      "Target": "Parameter",
      "Id": "ParamSX3",
      "Segments": [
        0,
        0,
        0,
        0.233,
        0.9,
        0,
        0.533,
        -0.1,
        0,
        1.267,
        0,
        2,
        4,
        0
      ]
    },
    {
      "Target": "Parameter",
      "Id": "ParamRSB",
      "Segments": [
        0,
        0,
        0,
        2,
        10,
        2,
        2.033,
        0,
        2,
        4,
        0
      ]
    },
    {
      "Target": "Parameter",
      "Id": "ParamOpaishakeX",
      "Segments": [
        0,
        -0.376,
        0,
        0.367,
        0.099,
        1,
        0.478,
        0.099,
        0.589,
        -0.841,
        0.7,
        -0.848,
        1,
        0.822,
        -0.856,
        0.945,
        -0.096,
        1.067,
        -0.086,
        1,
        1.189,
        -0.076,
        1.311,
        -0.602,
        1.433,
        -0.601,
        1,
        1.544,
        -0.6,
        1.656,
        -0.31,
        1.767,
        -0.303,
        1,
        1.934,
        -0.293,
        2.1,
        -0.499,
        2.267,
        -0.502,
        1,
        2.445,
        -0.505,
        2.622,
        -0.379,
        2.8,
        -0.376,
        1,
        3.2,
        -0.368,
        3.6,
        -0.376,
        4,
        -0.376
      ]
    },
    {
      "Target": "Parameter",
      "Id": "ParamOpaishakeY",
      "Segments": [
        0,
        0.318,
        0,
        0.333,
        0.878,
        1,
        0.444,
        0.878,
        0.556,
        -0.5,
        0.667,
        -0.513,
        1,
        0.789,
        -0.459,
        0.911,
        0.385,
        1.033,
        0.4,
        1,
        1.155,
        0.421,
        1.278,
        -0.128,
        1.4,
        -0.123,
        1,
        1.533,
        -0.117,
        1.667,
        0.11,
        1.8,
        0.129,
        1,
        1.978,
        0.154,
        2.155,
        -0.057,
        2.333,
        -0.048,
        1,
        2.489,
        -0.041,
        2.644,
        0.024,
        2.8,
        0.07,
        1,
        2.944,
        0.112,
        3.089,
        -0.713,
        3.233,
        -0.706,
        1,
        3.489,
        -0.694,
        3.744,
        0.318,
        4,
        0.318
      ]
    },
    {
      "Target": "Parameter",
      "Id": "ParamHairFront",
      "Segments": [
        0,
        0,
        0,
        0.3,
        0.9,
        1,
        0.422,
        0.9,
        0.545,
        -0.984,
        0.667,
        -1,
        1,
        0.911,
        -1,
        1.156,
        0.924,
        1.4,
        1,
        0,
        1.933,
        0.4,
        0,
        2.5,
        1,
        1,
        2.789,
        0.838,
        3.078,
        0.129,
        3.367,
        -0.102,
        1,
        3.578,
        -0.272,
        3.789,
        0,
        4,
        0
      ]
    },
    {
      "Target": "Parameter",
      "Id": "ParamHaiFrontY",
      "Segments": [
        0,
        0.463,
        0,
        0.467,
        0.9,
        1,
        0.589,
        0.9,
        0.711,
        -0.984,
        0.833,
        -1,
        1,
        1.078,
        -1,
        1.322,
        0.924,
        1.567,
        1,
        0,
        2.1,
        0.4,
        0,
        2.667,
        1,
        1,
        2.956,
        0.838,
        3.244,
        0.129,
        3.533,
        -0.102,
        1,
        3.689,
        -0.227,
        3.844,
        0.463,
        4,
        0.463
      ]
    },
    {
      "Target": "Parameter",
      "Id": "ParamHairFront2",
      "Segments": [
        0,
        0.234,
        0,
        0.3,
        0.9,
        1,
        0.422,
        0.9,
        0.545,
        -0.984,
        0.667,
        -1,
        1,
        0.911,
        -1,
        1.156,
        0.924,
        1.4,
        1,
        0,
        1.933,
        0.4,
        0,
        2.5,
        1,
        1,
        2.789,
        0.838,
        3.078,
        0.129,
        3.367,
        -0.102,
        1,
        3.578,
        -0.272,
        3.789,
        0.234,
        4,
        0.234
      ]
    },
    {
      "Target": "Parameter",
      "Id": "ParamHairFront2Y",
      "Segments": [
        0,
        0.604,
        0,
        0.5,
        0.9,
        1,
        0.622,
        0.9,
        0.745,
        -0.984,
        0.867,
        -1,
        1,
        1.111,
        -1,
        1.356,
        0.924,
        1.6,
        1,
        0,
        2.133,
        0.4,
        0,
        2.7,
        1,
        1,
        2.989,
        0.838,
        3.278,
        0.129,
        3.567,
        -0.102,
        1,
        3.711,
        -0.218,
        3.856,
        0.604,
        4,
        0.604
      ]
    },
    {
      "Target": "Parameter",
      "Id": "ParamHairFront3",
      "Segments": [
        0,
        -0.261,
        0,
        0.367,
        0.9,
        1,
        0.489,
        0.9,
        0.611,
        -0.984,
        0.733,
        -1,
        1,
        0.978,
        -1,
        1.222,
        0.924,
        1.467,
        1,
        0,
        2,
        0.4,
        0,
        2.567,
        1,
        1,
        2.856,
        0.838,
        3.144,
        0.129,
        3.433,
        -0.102,
        1,
        3.622,
        -0.254,
        3.811,
        -0.261,
        4,
        -0.261
      ]
    },
    {
      "Target": "Parameter",
      "Id": "ParamHairFront3Y",
      "Segments": [
        0,
        0.234,
        0,
        0.533,
        0.9,
        1,
        0.655,
        0.9,
        0.778,
        -0.984,
        0.9,
        -1,
        1,
        1.144,
        -1,
        1.389,
        0.924,
        1.633,
        1,
        0,
        2.167,
        0.4,
        0,
        2.733,
        1,
        1,
        3.022,
        0.838,
        3.311,
        0.129,
        3.6,
        -0.102,
        1,
        3.733,
        -0.209,
        3.867,
        0.234,
        4,
        0.234
      ]
    },
    {
      "Target": "Parameter",
      "Id": "ParamHairSide",
      "Segments": [
        0,
        0.09,
        0,
        0.233,
        0.9,
        1,
        0.355,
        0.9,
        0.478,
        -0.984,
        0.6,
        -1,
        1,
        0.844,
        -1,
        1.089,
        0.924,
        1.333,
        1,
        0,
        1.867,
        0.4,
        0,
        2.433,
        1,
        1,
        2.722,
        0.838,
        3.011,
        0.129,
        3.3,
        -0.102,
        1,
        3.533,
        -0.29,
        3.767,
        0.09,
        4,
        0.09
      ]
    },
    {
      "Target": "Parameter",
      "Id": "ParamHairFrontY",
      "Segments": [
        0,
        0.465,
        0,
        0.467,
        0.9,
        1,
        0.589,
        0.9,
        0.711,
        -0.984,
        0.833,
        -1,
        1,
        1.078,
        -1,
        1.322,
        0.924,
        1.567,
        1,
        0,
        2.1,
        0.4,
        0,
        2.667,
        1,
        1,
        2.956,
        0.838,
        3.244,
        0.129,
        3.533,
        -0.102,
        1,
        3.689,
        -0.227,
        3.844,
        0.465,
        4,
        0.465
      ]
    },
    {
      "Target": "Parameter",
      "Id": "ParamHairSide2",
      "Segments": [
        0,
        -0.146,
        0,
        0.3,
        0.9,
        1,
        0.422,
        0.9,
        0.545,
        -0.984,
        0.667,
        -1,
        1,
        0.911,
        -1,
        1.156,
        0.924,
        1.4,
        1,
        0,
        1.933,
        0.4,
        0,
        2.5,
        1,
        1,
        2.789,
        0.838,
        3.078,
        0.129,
        3.367,
        -0.102,
        1,
        3.578,
        -0.272,
        3.789,
        -0.146,
        4,
        -0.146
      ]
    },
    {
      "Target": "Parameter",
      "Id": "ParamHairSide2y",
      "Segments": [
        0,
        0.285,
        0,
        0.533,
        0.9,
        1,
        0.655,
        0.9,
        0.778,
        -0.984,
        0.9,
        -1,
        1,
        1.144,
        -1,
        1.389,
        0.924,
        1.633,
        1,
        0,
        2.167,
        0.4,
        0,
        2.733,
        1,
        1,
        3.022,
        0.838,
        3.311,
        0.129,
        3.6,
        -0.102,
        1,
        3.733,
        -0.209,
        3.867,
        0.285,
        4,
        0.285
      ]
    },
    {
      "Target": "Parameter",
      "Id": "ParamES",
      "Segments": [
        0,
        3.98,
        0,
        0.433,
        9,
        1,
        0.555,
        9,
        0.678,
        -9.842,
        0.8,
        -10,
        1,
        1.044,
        -10,
        1.289,
        9.24,
        1.533,
        10,
        0,
        2.067,
        4,
        0,
        2.633,
        10,
        1,
        2.922,
        8.38,
        3.211,
        -0.373,
        3.5,
        -2.685,
        1,
        3.667,
        -4.025,
        3.833,
        3.98,
        4,
        3.98
      ]
    },
    {
      "Target": "Parameter",
      "Id": "ParamHairBack",
      "Segments": [
        0,
        0,
        0,
        0.467,
        1,
        0,
        1,
        -0.7,
        0,
        1.567,
        0.8,
        0,
        2.233,
        -0.574,
        0,
        3.167,
        0.693,
        0,
        4,
        0
      ]
    },
    {
      "Target": "Parameter",
      "Id": "ParamHairBackY",
      "Segments": [
        0,
        0.549,
        0,
        0.733,
        1,
        0,
        1.267,
        -0.7,
        0,
        1.833,
        0.8,
        0,
        2.5,
        -0.574,
        0,
        3.433,
        0.693,
        0,
        4,
        0.549
      ]
    },
    {
      "Target": "Parameter",
      "Id": "ParamHairBack2",
      "Segments": [
        0,
        0.356,
        0,
        0.367,
        1,
        0,
        0.9,
        -0.7,
        0,
        1.467,
        0.8,
        0,
        2.133,
        -0.574,
        0,
        3.067,
        0.693,
        0,
        4,
        0.356
      ]
    },
    {
      "Target": "Parameter",
      "Id": "ParamHairBack2Y",
      "Segments": [
        0,
        0.667,
        0,
        0.733,
        1,
        0,
        1.267,
        -0.7,
        0,
        1.833,
        0.8,
        0,
        2.5,
        -0.574,
        0,
        3.433,
        0.693,
        0,
        4,
        0.667
      ]
    },
    {
      "Target": "Parameter",
      "Id": "ParamClothes",
      "Segments": [
        0,
        0,
        0,
        0.567,
        -1,
        0,
        0.967,
        1,
        0,
        1.633,
        -0.781,
        0,
        2.3,
        0.47,
        0,
        3.333,
        -1,
        0,
        4,
        0
      ]
    },
    {
      "Target": "Parameter",
      "Id": "ParamClothesY",
      "Segments": [
        0,
        -0.487,
        0,
        0.833,
        -1,
        0,
        1.233,
        1,
        0,
        1.9,
        -0.781,
        0,
        2.567,
        0.47,
        0,
        3.6,
        -1,
        0,
        4,
        -0.487
      ]
    },
    {
      "Target": "Parameter",
      "Id": "ParamClothes2",
      "Segments": [
        0,
        -0.243,
        0,
        0.633,
        -1,
        0,
        1.033,
        1,
        0,
        1.7,
        -0.781,
        0,
        2.367,
        0.47,
        0,
        3.4,
        -1,
        0,
        4,
        -0.243
      ]
    },
    {
      "Target": "Parameter",
      "Id": "ParamClothes2Y",
      "Segments": [
        0,
        -0.602,
        0,
        0.9,
        -1,
        0,
        1.3,
        1,
        0,
        1.967,
        -0.781,
        0,
        2.633,
        0.47,
        0,
        3.667,
        -1,
        0,
        4,
        -0.602
      ]
    },
    {
      "Target": "Parameter",
      "Id": "ParamSkirt",
      "Segments": [
        0,
        -0.267,
        0,
        0.467,
        -1,
        0,
        0.867,
        1,
        0,
        1.533,
        -0.781,
        0,
        2.2,
        0.47,
        0,
        3.233,
        -1,
        0,
        4,
        -0.267
      ]
    },
    {
      "Target": "Parameter",
      "Id": "ParamSkirtY",
      "Segments": [
        0,
        0.005,
        0,
        0.733,
        -1,
        0,
        1.133,
        1,
        0,
        1.8,
        -0.781,
        0,
        2.467,
        0.47,
        0,
        3.5,
        -1,
        0,
        4,
        0.005
      ]
    },
    {
      "Target": "Parameter",
      "Id": "ParamSkirt2",
      "Segments": [
        0,
        0,
        0,
        0.567,
        -1,
        0,
        0.967,
        1,
        0,
        1.633,
        -0.781,
        0,
        2.3,
        0.47,
        0,
        3.333,
        -1,
        0,
        4,
        0
      ]
    },
    {
      "Target": "Parameter",
      "Id": "ParamSkirt2Y",
      "Segments": [
        0,
        -0.11,
        0,
        0.833,
        -1,
        0,
        1.233,
        1,
        0,
        1.9,
        -0.781,
        0,
        2.567,
        0.47,
        0,
        3.6,
        -1,
        0,
        4,
        -0.11
      ]
    },
    {
      "Target": "Parameter",
      "Id": "ParamSkirt3",
      "Segments": [
        0,
        -0.079,
        0,
        0.7,
        -1,
        0,
        1.1,
        1,
        0,
        1.767,
        -0.781,
        0,
        2.433,
        0.47,
        0,
        3.467,
        -1,
        0,
        4,
        -0.079
      ]
    },
    {
      "Target": "Parameter",
      "Id": "ParamSkirt2Y2",
      "Segments": [
        0,
        0,
        0,
        0.967,
        -1,
        0,
        1.367,
        1,
        0,
        2.033,
        -0.781,
        0,
        2.7,
        0.47,
        0,
        3.733,
        -1,
        0,
        4,
        0
      ]
    },
    {
      "Target": "Parameter",
      "Id": "ParamSkirt4",
      "Segments": [
        0,
        -0.267,
        0,
        0.467,
        -1,
        0,
        0.867,
        1,
        0,
        1.533,
        -0.781,
        0,
        2.2,
        0.47,
        0,
        3.233,
        -1,
        0,
        4,
        -0.267
      ]
    },
    {
      "Target": "Parameter",
      "Id": "ParamSkirt2Y3",
      "Segments": [
        0,
        0,
        0,
        0.733,
        -1,
        0,
        1.133,
        1,
        0,
        1.8,
        -0.781,
        0,
        2.467,
        0.47,
        0,
        3.5,
        -1,
        0,
        4,
        0
      ]
    },
    {
      "Target": "Parameter",
      "Id": "ParamEyeSmile",
      "Segments": [
        0,
        0,
        0,
        4,
        0
      ]
    },
    {
      "Target": "Parameter",
      "Id": "ParamParamBrowLY",
      "Segments": [
        0,
        0,
        0,
        4,
        0
      ]
    },
    {
      "Target": "Parameter",
      "Id": "ParamParamBrowRY",
      "Segments": [
        0,
        0,
        0,
        4,
        0
      ]
    },
    {
      "Target": "Parameter",
      "Id": "ParamBrowLAngle",
      "Segments": [
        0,
        0,
        0,
        4,
        0
      ]
    },
    {
      "Target": "Parameter",
      "Id": "ParamBrowRAngle",
      "Segments": [
        0,
        0,
        0,
        4,
        0
      ]
    },
    {
      "Target": "Parameter",
      "Id": "ParamBreath",
      "Segments": [
        0,
        0,
        0,
        4,
        0
      ]
    },
    {
      "Target": "Parameter",
      "Id": "ParamPJZY",
      "Segments": [
        0,
        0,
        0,
        4,
        0
      ]
    },
    {
      "Target": "Parameter",
      "Id": "ParamArmLY",
      "Segments": [
        0,
        0,
        0,
        4,
        0
      ]
    },
    {
      "Target": "Parameter",
      "Id": "ParamZSH",
      "Segments": [
        0,
        0,
        0,
        4,
        0
      ]
    },
    {
      "Target": "Parameter",
      "Id": "ZPJSW",
      "Segments": [
        0,
        -0.573,
        0,
        4,
        -0.573
      ]
    },
    {
      "Target": "Parameter",
      "Id": "ParamZPJW2",
      "Segments": [
        0,
        -0.022,
        0,
        4,
        -0.022
      ]
    },
    {
      "Target": "Parameter",
      "Id": "ParamZPJW5",
      "Segments": [
        0,
        0.292,
        0,
        4,
        0.292
      ]
    },
    {
      "Target": "Parameter",
      "Id": "ParamZPJW7",
      "Segments": [
        0,
        0.292,
        0,
        4,
        0.292
      ]
    },
    {
      "Target": "Parameter",
      "Id": "ParamZPJW6",
      "Segments": [
        0,
        -0.022,
        0,
        4,
        -0.022
      ]
    },
    {
      "Target": "Parameter",
      "Id": "ParamSDS",
      "Segments": [
        0,
        0,
        0,
        4,
        0
      ]
    },
    {
      "Target": "Parameter",
      "Id": "ParamYJJ",
      "Segments": [
        0,
        0,
        0,
        4,
        0
      ]
    },
    {
      "Target": "Parameter",
      "Id": "ParamHandR2",
      "Segments": [
        0,
        0,
        0,
        4,
        0
      ]
    },
    {
      "Target": "Parameter",
      "Id": "Param3YSH",
      "Segments": [
        0,
        0,
        0,
        4,
        0
      ]
    },
    {
      "Target": "Parameter",
      "Id": "ParamYGZD",
      "Segments": [
        0,
        0,
        0,
        4,
        0
      ]
    },
    {
      "Target": "Parameter",
      "Id": "ParamYPJDS",
      "Segments": [
        0,
        0,
        0,
        4,
        0
      ]
    },
    {
      "Target": "Parameter",
      "Id": "ParamDZYC",
      "Segments": [
        0,
        0,
        0,
        4,
        0
      ]
    },
    {
      "Target": "Parameter",
      "Id": "ParamT",
      "Segments": [
        0,
        0,
        0,
        4,
        0
      ]
    },
    {
      "Target": "Parameter",
      "Id": "ParamLegL",
      "Segments": [
        0,
        0.098,
        0,
        4,
        0.098
      ]
    },
    {
      "Target": "Parameter",
      "Id": "ParamLegL1",
      "Segments": [
        0,
        0,
        0,
        4,
        0
      ]
    },
    {
      "Target": "Parameter",
      "Id": "ParamLegLY",
      "Segments": [
        0,
        -0.043,
        0,
        4,
        -0.043
      ]
    },
    {
      "Target": "Parameter",
      "Id": "ParamLegL1Y",
      "Segments": [
        0,
        0,
        0,
        4,
        0
      ]
    },
    {
      "Target": "Parameter",
      "Id": "ParamPB14",
      "Segments": [
        0,
        0,
        0,
        4,
        0
      ]
    },
    {
      "Target": "Parameter",
      "Id": "ParamRSB2",
      "Segments": [
        0,
        0,
        0,
        4,
        0
      ]
    },
    {
      "Target": "Parameter",
      "Id": "ParamRSB3",
      "Segments": [
        0,
        0,
        0,
        4,
        0
      ]
    },
    {
      "Target": "Parameter",
      "Id": "ParamWX",
      "Segments": [
        0,
        0,
        0,
        4,
        0
      ]
    },
    {
      "Target": "Parameter",
      "Id": "ParamWY",
      "Segments": [
        0,
        0,
        0,
        4,
        0
      ]
    },
    {
      "Target": "Parameter",
      "Id": "ParamWZoom",
      "Segments": [
        0,
        0,
        0,
        4,
        0
      ]
    },
    {
      "Target": "Parameter",
      "Id": "BG",
      "Segments": [
        0,
        0,
        0,
        4,
        0
      ]
    },
    {
      "Target": "Parameter",
      "Id": "ParamBLACK1",
      "Segments": [
        0,
        0,
        0,
        4,
        0
      ]
    },
    {
      "Target": "Parameter",
      "Id": "ParamBlack0",
      "Segments": [
        0,
        0,
        0,
        4,
        0
      ]
    }
  ],
  "UserData": [
    {
      "Time": 0.0,
      "Value": ""
    }
  ]
}